[
    {
        "id": 1,
        "title": "Amilla Fushi Madlives"
    },
    {
        "id": 2,
        "title": "Anantara Dhigu Resort  Maldives"
    },
    {
        "id": 3,
        "title": "Anantara Kihavah Villas  Maldives"
    },
    {
        "id": 4,
        "title": "Baglioni Resort Maldives"
    },
    {
        "id": 5,
        "title": "Cheval Blanc Randheli Maldives"
    },
    {
        "id": 6,
        "title": "Coco Privé Private Island Maldives"
    },
    {
        "id": 7,
        "title": "COMO Maalifushi Maldives"
    },
    {
        "id": 8,
        "title": "Conrad Rangali Maldives "
    },
    {
        "id": 9,
        "title": "Fairmont Sirru Fen Fushi Maldives"
    },
    {
        "id": 10,
        "title": "Finolhu Maldives"
    },
    {
        "id": 11,
        "title": "Four Seasons Explorer Maldives"
    },
    {
        "id": 12,
        "title": "Four Seasons Kuda Huraa Maldives"
    },
    {
        "id": 13,
        "title": "Four Seasons Landaa Giraavaru Maldives"
    },
    {
        "id": 14,
        "title": "Hideaway Beach Resort Maldives"
    },
    {
        "id": 15,
        "title": "Huvafen Fushi Maldives"
    },
    {
        "id": 16,
        "title": "JA Manafaru Maldives"
    },
    {
        "id": 17,
        "title": "Joali Maldives"
    },
    {
        "id": 18,
        "title": "Jumeirah Vittaveli Maldives"
    },
    {
        "id": 19,
        "title": "Kanuhura Maldives"
    },
    {
        "id": 20,
        "title": "Naladhu Private Island Maldives"
    },
    {
        "id": 21,
        "title": "Niyama Private Islands Maldives"
    },
    {
        "id": 22,
        "title": "One & Only Reethi Rah Maldives"
    },
    {
        "id": 23,
        "title": "Park Hyatt Hadahaa Maldives"
    },
    {
        "id": 24,
        "title": "Shangri-La's Villingili Maldives"
    },
    {
        "id": 25,
        "title": "Six Senses Laamu Maldives"
    },
    {
        "id": 26,
        "title": "Soneva Fushi Maldives"
    },
    {
        "id": 27,
        "title": "Soneva Jani Maldives"
    },
    {
        "id": 28,
        "title": "The St. Regis Vommuli Resort Maldives"
    },
    {
        "id": 29,
        "title": "Vakkaru Maldives"
    },
    {
        "id": 30,
        "title": "Velaa Private Island Maldives"
    },
    {
        "id": 31,
        "title": "W Maldives Maldives"
    }
]